{"cameraMode":{"drawMode":0,"name":"Shaded","section":"Shading Mode"},"sceneLighting":false,"audioPlay":false,"sceneViewState":{"m_AlwaysRefresh":false,"showFog":true,"showSkybox":false,"showFlares":true,"showImageEffects":true,"showParticleSystems":true,"showVisualEffectGraphs":true,"m_FxEnabled":true},"in2DMode":false,"pivot":{"x":-8.479728698730469,"y":-5.557188987731934,"z":11.510714530944825},"rotation":{"x":-0.2349187135696411,"y":-0.34180769324302676,"z":0.0886659026145935,"w":-0.9056069254875183},"size":10.0,"orthographic":false}